sarp_utils/__init__.py
sarp_utils/bitfield_utils.py
sarp_utils/codec.py
sarp_utils/fill_command_codec.py
sarp_utils/fill_telem_codec.py
sarp_utils/flight_data_codec.py
sarp_utils/network_node.py
sarp_utils/prop_command_codec.py
sarp_utils/prop_telem_codec.py
sarp_utils/template_codec.py
sarp_utils/thermocouple_codec.py
sarp_utils-1.2.15.dist-info/LICENSE
sarp_utils-1.2.15.dist-info/METADATA
sarp_utils-1.2.15.dist-info/WHEEL
sarp_utils-1.2.15.dist-info/top_level.txt
sarp_utils-1.2.15.dist-info/RECORD
