Metadata-Version: 2.1
Name: sarp_utils
Version: 1.2.15
Summary: A package to encode network communication for SARP
Home-page: https://gitlab.com/SARP_UW/codecs
Author: Matthew He
Author-email: mhe9467@uw.edu
Classifier: Programming Language :: Python :: 3
Classifier: License :: OSI Approved :: MIT License
Classifier: Operating System :: OS Independent
Requires-Python: >=3.5
License-File: LICENSE
